LICENSE
README.rst
setup.py
arclet/cesloi/__init__.py
arclet/cesloi/bot_client.py
arclet/cesloi/communicate_with_mah.py
arclet/cesloi/exceptions.py
arclet/cesloi/interrupts.py
arclet/cesloi/logger.py
arclet/cesloi/mini.py
arclet/cesloi/plugin.py
arclet/cesloi/utils.py
arclet/cesloi/event/__init__.py
arclet/cesloi/event/base.py
arclet/cesloi/event/inserter.py
arclet/cesloi/event/lifecycle.py
arclet/cesloi/event/messages.py
arclet/cesloi/event/mirai.py
arclet/cesloi/message/__init__.py
arclet/cesloi/message/command.py
arclet/cesloi/message/element.py
arclet/cesloi/message/messageChain.py
arclet/cesloi/message/utils.py
arclet/cesloi/message/alconna/__init__.py
arclet/cesloi/message/alconna/utils.py
arclet/cesloi/model/__init__.py
arclet/cesloi/model/relation.py
arclet/cesloi/model/utils.py
arclet/cesloi/timing/__init__.py
arclet/cesloi/timing/event.py
arclet/cesloi/timing/schedule.py
arclet/cesloi/timing/task.py
arclet/cesloi/timing/timers.py
cesloi.egg-info/PKG-INFO
cesloi.egg-info/SOURCES.txt
cesloi.egg-info/dependency_links.txt
cesloi.egg-info/requires.txt
cesloi.egg-info/top_level.txt