Metadata-Version: 2.1
Name: cesloi
Version: 0.6.11
Summary: An simple Python SDK base on mirai-api-http v2
Home-page: https://github.com/RF-Tar-Railt/Cesloi
Author: ArcletProject
Author-email: rf_tar_railt@qq.com
License: AGPL 3.0
Keywords: mirai,bot,asyncio,http,websocket
Platform: UNKNOWN
Classifier: Programming Language :: Python :: 3.8
Classifier: Programming Language :: Python :: 3.9
Classifier: Operating System :: OS Independent
Requires-Python: >=3.8
License-File: LICENSE
